kerala_math/__init__.py
kerala_math/jyatable/__init__.py
kerala_math/jyatable/aryabhata.py
kerala_math/jyatable/laghuvivrti.py
kerala_math/jyatable/madhava.py
kerala_math/jyatable/tantrasangraha.py
kerala_math/jyatable/tattajjya.py
kerala_math/series/__init__.py
kerala_math/series/circumference.py
kerala_math/series/jya.py
kerala_math-0.0.2.dist-info/LICENSE
kerala_math-0.0.2.dist-info/METADATA
kerala_math-0.0.2.dist-info/WHEEL
kerala_math-0.0.2.dist-info/top_level.txt
kerala_math-0.0.2.dist-info/RECORD
